local_cd_search/__init__.py
local_cd_search/annotate.py
local_cd_search/download.py
local_cd_search/logger.py
local_cd_search/main.py
local_cd_search/parser.py
local_cd_search/py.typed
local_cd_search/utils.py
local_cd_search-0.3.0.dist-info/WHEEL
local_cd_search-0.3.0.dist-info/entry_points.txt
local_cd_search-0.3.0.dist-info/METADATA
local_cd_search-0.3.0.dist-info/RECORD
