Metadata-Version: 2.3
Name: local-cd-search
Version: 0.3.0
Summary: Protein annotation using local PSSM databases from CDD
Author: Antonio Camargo
Author-email: Antonio Camargo <antoniop.camargo@gmail.com>
License: MIT License
Requires-Dist: click>=8.3.1
Requires-Dist: rich>=14.2.0
Requires-Dist: rich-click>=1.9.4
Requires-Python: >=3.10
